Metadata-Version: 2.1
Name: coindesk
Version: 0.2.0
Summary: Bitcoin current and historical price
Home-page: https://github.com/sdediego/coindesk-api-client
Author: Sergio de Diego
Author-email: sergiodediego@outlook.com
License: MIT
Download-URL: https://github.com/sdediego/coindesk-api-client/archive/v0.2.0-alpha.tar.gz
Keywords: coindesk bitcoin blockchain api client Python
Platform: UNKNOWN
Classifier: Development Status :: 3 - Alpha
Classifier: Intended Audience :: Developers
Classifier: Intended Audience :: Financial and Insurance Industry
Classifier: License :: OSI Approved :: MIT License
Classifier: Natural Language :: English
Classifier: Operating System :: OS Independent
Classifier: Programming Language :: Python
Classifier: Programming Language :: Python :: 3
Classifier: Programming Language :: Python :: 3.7
Classifier: Topic :: Office/Business :: Financial
Classifier: Topic :: Software Development :: Libraries
Classifier: Topic :: Software Development :: Libraries :: Python Modules
